test/test.v
module test(A, B, C, D, E);

   output D, E;
   input  A, B, C;
   wire   w1;

   and G1(w1, A, B);
   not G2(E, C);
   or  G3(D, w1, E);

endmodule

test/test_tb.v
`timescale 1ns/100ps
`include "test.v"

module test_tb;

   wire A, B, C, D, E;
   integer k=0;

   assign {A,B,C} = k;
   test the_circuit(A, B, C, D, E);

   initial begin

      $dumpfile("test.vcd");
      $dumpvars(0, test_tb);

      for (k=0; k<8; k=k+1)
        #10 $display("done testing case %d", k);

      $finish;

   end

endmodule

test/test.vcd
$date
	Tue Dec 29 16:05:38 2020
$end
$version
	Icarus Verilog
$end
$timescale
	100ps
$end
$scope module test_tb $end
$var wire 1 ! E $end
$var wire 1 " D $end
$var wire 1 # C $end
$var wire 1 $ B $end
$var wire 1 % A $end
$var integer 32 & k [31:0] $end
$scope module the_circuit $end
$var wire 1 % A $end
$var wire 1 $ B $end
$var wire 1 # C $end
$var wire 1 " D $end
$var wire 1 ! E $end
$var wire 1 ' w1 $end
$upscope $end
$upscope $end
$enddefinitions $end
#0
$dumpvars
0'
b0 &
0%
0$
0#
1"
1!
$end
#100
0"
0!
1#
b1 &
#200
1"
1!
0#
1$
b10 &
#300
0"
0!
1#
b11 &
#400
1"
1!
0#
0$
1%
b100 &
#500
0"
0!
1#
b101 &
#600
1"
1!
1'
0#
1$
b110 &
#700
0!
1#
b111 &
#800
1!
0'
0#
0$
0%
b1000 &
